backend/__init__.py
backend/config.py
backend/config.toml
backend/file_handler.py
backend/services.py
backend/strategy.py
terminal_note-0.10.0.dist-info/licenses/LICENSE
terminal_note-0.10.0.dist-info/METADATA
terminal_note-0.10.0.dist-info/WHEEL
terminal_note-0.10.0.dist-info/entry_points.txt
terminal_note-0.10.0.dist-info/top_level.txt
terminal_note-0.10.0.dist-info/RECORD
