Metadata-Version: 2.4
Name: terminal-note
Version: 0.10.0
Summary: Простая консольная утилита для управления файлами заметок.
Author-email: Belousov Sergey <belousovsergej56@gmail.com>
License: MIT
Project-URL: Homepage, https://github.com/belousovsergey56/terminal-note
Project-URL: Issues, https://github.com/belousovsergey56/terminal-note/issues
Classifier: Programming Language :: Python :: 3
Classifier: Programming Language :: Python :: 3.11
Requires-Python: >=3.11
License-File: LICENSE
Requires-Dist: frogmouth>=0.9.2
Requires-Dist: iterfzf>=1.8.0.62.0
Dynamic: license-file
